fine_search/__init__.py
fine_search/fine_search.py
fine_search/text_sims.py
dj_fine_search-0.0.4.dist-info/LICENSE.txt
dj_fine_search-0.0.4.dist-info/METADATA
dj_fine_search-0.0.4.dist-info/WHEEL
dj_fine_search-0.0.4.dist-info/top_level.txt
dj_fine_search-0.0.4.dist-info/RECORD
