Metadata-Version: 2.1
Name: dj-fine-search
Version: 0.0.4
Summary: A key word based queryset search for django
Home-page: https://github.com/bellomusodiq/dj-fine-search
Author: Mayowa Bello
Author-email: bmayowa25@gmail.com
License: UNKNOWN
Platform: UNKNOWN
Classifier: Programming Language :: Python :: 3
Classifier: License :: OSI Approved :: MIT License
Classifier: Operating System :: OS Independent
Requires-Python: >=3.5
